[
  {
    "threshold": 0.05,
    "tp": 99,
    "fp": 1812,
    "tn": 88,
    "fn": 1,
    "precision": 0.05180533751962323,
    "recall": 0.99,
    "f1": 0.09845847836897066,
    "cost": 1822.0
  },
  {
    "threshold": 0.1,
    "tp": 93,
    "fp": 990,
    "tn": 910,
    "fn": 7,
    "precision": 0.08587257617728532,
    "recall": 0.93,
    "f1": 0.15722738799661878,
    "cost": 1060.0
  },
  {
    "threshold": 0.15,
    "tp": 84,
    "fp": 308,
    "tn": 1592,
    "fn": 16,
    "precision": 0.21428571428571427,
    "recall": 0.84,
    "f1": 0.3414634146341463,
    "cost": 468.0
  },
  {
    "threshold": 0.2,
    "tp": 82,
    "fp": 112,
    "tn": 1788,
    "fn": 18,
    "precision": 0.422680412371134,
    "recall": 0.82,
    "f1": 0.5578231292517007,
    "cost": 292.0
  },
  {
    "threshold": 0.25,
    "tp": 79,
    "fp": 39,
    "tn": 1861,
    "fn": 21,
    "precision": 0.6694915254237288,
    "recall": 0.79,
    "f1": 0.7247706422018348,
    "cost": 249.0
  },
  {
    "threshold": 0.3,
    "tp": 79,
    "fp": 15,
    "tn": 1885,
    "fn": 21,
    "precision": 0.8404255319148937,
    "recall": 0.79,
    "f1": 0.8144329896907218,
    "cost": 225.0
  },
  {
    "threshold": 0.35,
    "tp": 79,
    "fp": 9,
    "tn": 1891,
    "fn": 21,
    "precision": 0.8977272727272727,
    "recall": 0.79,
    "f1": 0.8404255319148937,
    "cost": 219.0
  },
  {
    "threshold": 0.4,
    "tp": 79,
    "fp": 9,
    "tn": 1891,
    "fn": 21,
    "precision": 0.8977272727272727,
    "recall": 0.79,
    "f1": 0.8404255319148937,
    "cost": 219.0
  },
  {
    "threshold": 0.45,
    "tp": 79,
    "fp": 9,
    "tn": 1891,
    "fn": 21,
    "precision": 0.8977272727272727,
    "recall": 0.79,
    "f1": 0.8404255319148937,
    "cost": 219.0
  },
  {
    "threshold": 0.5,
    "tp": 79,
    "fp": 9,
    "tn": 1891,
    "fn": 21,
    "precision": 0.8977272727272727,
    "recall": 0.79,
    "f1": 0.8404255319148937,
    "cost": 219.0
  },
  {
    "threshold": 0.55,
    "tp": 79,
    "fp": 9,
    "tn": 1891,
    "fn": 21,
    "precision": 0.8977272727272727,
    "recall": 0.79,
    "f1": 0.8404255319148937,
    "cost": 219.0
  },
  {
    "threshold": 0.6,
    "tp": 79,
    "fp": 9,
    "tn": 1891,
    "fn": 21,
    "precision": 0.8977272727272727,
    "recall": 0.79,
    "f1": 0.8404255319148937,
    "cost": 219.0
  },
  {
    "threshold": 0.65,
    "tp": 78,
    "fp": 9,
    "tn": 1891,
    "fn": 22,
    "precision": 0.896551724137931,
    "recall": 0.78,
    "f1": 0.8342245989304813,
    "cost": 229.0
  },
  {
    "threshold": 0.7,
    "tp": 77,
    "fp": 9,
    "tn": 1891,
    "fn": 23,
    "precision": 0.8953488372093024,
    "recall": 0.77,
    "f1": 0.8279569892473118,
    "cost": 239.0
  },
  {
    "threshold": 0.75,
    "tp": 77,
    "fp": 9,
    "tn": 1891,
    "fn": 23,
    "precision": 0.8953488372093024,
    "recall": 0.77,
    "f1": 0.8279569892473118,
    "cost": 239.0
  },
  {
    "threshold": 0.8,
    "tp": 73,
    "fp": 9,
    "tn": 1891,
    "fn": 27,
    "precision": 0.8902439024390244,
    "recall": 0.73,
    "f1": 0.8021978021978022,
    "cost": 279.0
  },
  {
    "threshold": 0.85,
    "tp": 66,
    "fp": 9,
    "tn": 1891,
    "fn": 34,
    "precision": 0.88,
    "recall": 0.66,
    "f1": 0.7542857142857142,
    "cost": 349.0
  },
  {
    "threshold": 0.9,
    "tp": 59,
    "fp": 7,
    "tn": 1893,
    "fn": 41,
    "precision": 0.8939393939393939,
    "recall": 0.59,
    "f1": 0.7108433734939759,
    "cost": 417.0
  },
  {
    "threshold": 0.95,
    "tp": 31,
    "fp": 2,
    "tn": 1898,
    "fn": 69,
    "precision": 0.9393939393939394,
    "recall": 0.31,
    "f1": 0.4661654135338345,
    "cost": 692.0
  }
]